{
  "hash": "359999f4",
  "browserHash": "6cd63888",
  "optimized": {
    "react": {
      "src": "../../node_modules/react/index.js",
      "file": "react.js",
      "fileHash": "b489e894",
      "needsInterop": true
    },
    "react-dom/client": {
      "src": "../../node_modules/react-dom/client.js",
      "file": "react-dom_client.js",
      "fileHash": "0fc1d30d",
      "needsInterop": true
    },
    "react-router-dom": {
      "src": "../../node_modules/react-router-dom/dist/index.js",
      "file": "react-router-dom.js",
      "fileHash": "0ba2cca9",
      "needsInterop": false
    }
  },
  "chunks": {
    "chunk-QSQYAWSL": {
      "file": "chunk-QSQYAWSL.js"
    }
  }
}